oauth2_cli_auth/__init__.py
oauth2_cli_auth/__version__.py
oauth2_cli_auth/_timeout.py
oauth2_cli_auth/_urllib_util.py
oauth2_cli_auth/code_grant.py
oauth2_cli_auth/conftest.py
oauth2_cli_auth/http_server.py
oauth2_cli_auth/simplified_flow.py
oauth2_cli_auth-2.0.0.dist-info/LICENSE
oauth2_cli_auth-2.0.0.dist-info/METADATA
oauth2_cli_auth-2.0.0.dist-info/WHEEL
oauth2_cli_auth-2.0.0.dist-info/RECORD
