Metadata-Version: 2.3
Name: oauth2-cli-auth
Version: 2.0.0
Summary: Authenticate against OAuth2 Provider in Python CLIs
License: MIT
Author: Timo Reymann
Author-email: mail@timo-reymann.de
Requires-Python: >=3.10
Classifier: Development Status :: 5 - Production/Stable
Classifier: Environment :: Console
Classifier: Environment :: MacOS X
Classifier: Intended Audience :: Developers
Classifier: Intended Audience :: System Administrators
Classifier: License :: OSI Approved :: MIT License
Classifier: Operating System :: POSIX
Classifier: Operating System :: Unix
Classifier: Programming Language :: Python :: 3
Classifier: Programming Language :: Python :: 3.10
Classifier: Programming Language :: Python :: 3.11
Classifier: Programming Language :: Python :: 3.12
Classifier: Programming Language :: Python :: 3.13
Project-URL: Bug Tracker, https://github.com/timo-reymann/python-oauth2-cli-auth/issues
Project-URL: Repository, https://github.com/timo-reymann/python-oauth2-cli-auth
